boardroom/__init__.py
boardroom/__main__.py
boardroom/errors.py
boardroom/functions.py
boardroom/params.py
boardroom/proposal.py
boardroom/protocol.py
boardroom/voter.py
boardroom-0.1.dist-info/LICENSE
boardroom-0.1.dist-info/METADATA
boardroom-0.1.dist-info/WHEEL
boardroom-0.1.dist-info/top_level.txt
boardroom-0.1.dist-info/RECORD
