Metadata-Version: 2.1
Name: boardroom
Version: 0.1
Summary: Boardroom in Python
Home-page: https://github.com/sepandhaghighi/boardroom
Author: Sepand Haghighi & Farzad Ramezani
Author-email: sepand@4r7.ir
License: MIT
Project-URL: Source, https://github.com/sepandhaghighi/boardroom
Project-URL: Tracker, https://github.com/sepandhaghighi/boardroom/issues
Keywords: boardroom
Platform: UNKNOWN
Classifier: Natural Language :: English
Classifier: License :: OSI Approved :: MIT License
Classifier: Operating System :: OS Independent
Classifier: Programming Language :: Python :: 3.5
Classifier: Programming Language :: Python :: 3.6
Classifier: Programming Language :: Python :: 3.7
Classifier: Programming Language :: Python :: 3.8
Classifier: Programming Language :: Python :: 3.9
Requires-Python: >=3.5
